zash_sdk/__init__.py
zash_sdk/_modidx.py
zash_sdk/collection.py
zash_sdk/connectors.py
zash_sdk/graph.py
zash_sdk/nft.py
zash_sdk/zash.py
zash_sdk-0.0.10.dist-info/LICENSE
zash_sdk-0.0.10.dist-info/METADATA
zash_sdk-0.0.10.dist-info/WHEEL
zash_sdk-0.0.10.dist-info/entry_points.txt
zash_sdk-0.0.10.dist-info/top_level.txt
zash_sdk-0.0.10.dist-info/RECORD
