Metadata-Version: 2.1
Name: zash-sdk
Version: 0.0.10
Summary: SDK
Home-page: https://github.com/zashdev/zash-sdk
Author: efx
Author-email: efe@joinzash.com
License: Apache Software License 2.0
Keywords: nbdev jupyter notebook python
Classifier: Development Status :: 4 - Beta
Classifier: Intended Audience :: Developers
Classifier: Natural Language :: English
Classifier: Programming Language :: Python :: 3.7
Classifier: Programming Language :: Python :: 3.8
Classifier: Programming Language :: Python :: 3.9
Classifier: Programming Language :: Python :: 3.10
Classifier: License :: OSI Approved :: Apache Software License
Requires-Python: >=3.7
License-File: LICENSE
Requires-Dist: boto3
Requires-Dist: pandas
Requires-Dist: redshift-connector
Requires-Dist: dateparser
Requires-Dist: requests
Requires-Dist: fastcore
Requires-Dist: python-box
Requires-Dist: web3
Provides-Extra: dev
